Metadata-Version: 1.0
Name: rmotr-com-jobs-detector
Version: 0.0.1
Summary: rmotr.com Group Project | Jobs Detector
Home-page: UNKNOWN
Author: rmotr.com
Author-email: questions@rmotr.com
License: CC BY-SA 4.0 License
Platform: UNKNOWN
